persian_ocr/__init__.py
persian_ocr/config.py
persian_ocr/core.py
persian_ocr/preprocessor.py
persian_ocr/utils.py
persian_ocr_toolkit-1.0.1.dist-info/licenses/LICENSE.txt
persian_ocr_toolkit-1.0.1.dist-info/METADATA
persian_ocr_toolkit-1.0.1.dist-info/WHEEL
persian_ocr_toolkit-1.0.1.dist-info/entry_points.txt
persian_ocr_toolkit-1.0.1.dist-info/top_level.txt
persian_ocr_toolkit-1.0.1.dist-info/RECORD
