Metadata-Version: 2.4
Name: persian-ocr-toolkit
Version: 1.0.1
Summary: کتابخانه حرفه‌ای OCR برای زبان فارسی
Home-page: https://github.com/MohammadHNdev/persian-ocr-toolkit
Author: MohammadHNdev
Author-email: hosein.norozi434@gmail.com
Project-URL: Bug Reports, https://github.com/MohammadHNdev/persian-ocr-toolkit/issues
Project-URL: Source, https://github.com/MohammadHNdev/persian-ocr-toolkit
Project-URL: Documentation, https://persian-ocr-toolkit.readthedocs.io/
Keywords: persian farsi ocr tesseract text-extraction pdf image-processing
Classifier: Development Status :: 4 - Beta
Classifier: Intended Audience :: Developers
Classifier: License :: OSI Approved :: MIT License
Classifier: Operating System :: OS Independent
Classifier: Programming Language :: Python :: 3
Classifier: Programming Language :: Python :: 3.8
Classifier: Programming Language :: Python :: 3.9
Classifier: Programming Language :: Python :: 3.10
Classifier: Programming Language :: Python :: 3.11
Classifier: Topic :: Scientific/Engineering :: Image Recognition
Classifier: Topic :: Text Processing :: Linguistic
Classifier: Natural Language :: Persian
Requires-Python: >=3.8
License-File: LICENSE.txt
Requires-Dist: numpy
Requires-Dist: opencv-python
Requires-Dist: Pillow
Requires-Dist: scikit-image
Requires-Dist: pytesseract
Requires-Dist: python-bidi
Requires-Dist: arabic-reshaper
Provides-Extra: dev
Requires-Dist: pytest>=6.0; extra == "dev"
Requires-Dist: black>=21.0; extra == "dev"
Requires-Dist: flake8>=3.8; extra == "dev"
Requires-Dist: mypy>=0.910; extra == "dev"
Requires-Dist: pytest-cov>=2.12; extra == "dev"
Provides-Extra: docs
Requires-Dist: sphinx>=4.0; extra == "docs"
Requires-Dist: sphinx-rtd-theme>=0.5; extra == "docs"
Dynamic: author
Dynamic: author-email
Dynamic: classifier
Dynamic: description
Dynamic: description-content-type
Dynamic: home-page
Dynamic: keywords
Dynamic: license-file
Dynamic: project-url
Dynamic: provides-extra
Dynamic: requires-dist
Dynamic: requires-python
Dynamic: summary
